optimap/_version.py
optimap/__init__.py
optimap/utils.py
optimap/_cpp.cpython-38-darwin.so
optimap/video/_importers.py
optimap/video/_load.py
optimap/video/_player.py
optimap/video/__init__.py
optimap/video/_edit.py
optimap/video/_export.py
optimap/video/_play.py
optimap/video/_filters.py
optimap/video/_save.py
optimap/phase/__init__.py
optimap/phase/_core.py
optimap/phase/_singularities.py
optimap/trace/_normalize.py
optimap/trace/_detrend.py
optimap/trace/__init__.py
optimap/trace/_core.py
optimap/trace/_interactive.py
optimap/trace/_point_clicker.py
optimap/trace/_points.py
optimap/trace/_compare.py
optimap/activation/__init__.py
optimap/activation/_core.py
optimap/motion/_warping.py
optimap/motion/_flowestimator.py
optimap/motion/__init__.py
optimap/motion/_core.py
optimap/motion/_plot.py
optimap/image/__init__.py
optimap/image/_core.py
optimap/image/_edit.py
optimap/image/_GHT.py
optimap/image/_segmenter.py
optimap/image/_mask.py
optimap/assets/visibility_on_symbol.png
optimap/assets/largest_component_symbol.png
optimap/assets/eraser_symbol.png
optimap/assets/redo_symbol.png
optimap/assets/visibility_off_symbol.png
optimap/assets/undo_symbol.png
optimap/assets/invert_symbol.png
optimap/assets/draw_symbol.png
optimap-0.3.1.dist-info/LICENSE.md
optimap-0.3.1.dist-info/RECORD
optimap-0.3.1.dist-info/WHEEL
optimap-0.3.1.dist-info/top_level.txt
optimap-0.3.1.dist-info/METADATA
