Metadata-Version: 2.2
Name: optimap
Version: 0.3.1
Summary: A toolbox for analyzing optical mapping and fluorescence imaging data.
Home-page: https://github.com/cardiacvision/optimap
Author: Jan Lebert
Author-email: jan.lebert@ucsf.edu
License: MIT
Classifier: Development Status :: 4 - Beta
Classifier: Intended Audience :: Developers
Classifier: Intended Audience :: Education
Classifier: Intended Audience :: Science/Research
Classifier: License :: OSI Approved :: MIT License
Classifier: Operating System :: MacOS
Classifier: Operating System :: POSIX :: Linux
Classifier: Operating System :: Microsoft :: Windows
Classifier: Programming Language :: Python :: 3.8
Classifier: Programming Language :: Python :: 3.9
Classifier: Programming Language :: Python :: 3.10
Classifier: Programming Language :: Python :: 3.11
Classifier: Programming Language :: Python :: 3.12
Classifier: Programming Language :: Python :: 3.13
Classifier: Topic :: Scientific/Engineering :: Image Processing
Classifier: Topic :: Scientific/Engineering :: Physics
Classifier: Topic :: Scientific/Engineering :: Medical Science Apps.
Requires-Python: >=3.8
License-File: LICENSE.md
Requires-Dist: matplotlib
Requires-Dist: mpl-pan-zoom
Requires-Dist: numpy
Requires-Dist: packaging
Requires-Dist: Pillow>=10.0.1
Requires-Dist: pooch
Requires-Dist: pymatreader
Requires-Dist: scikit-image
Requires-Dist: scikit-video
Requires-Dist: scipy
Requires-Dist: seasonal
Requires-Dist: static_ffmpeg
Requires-Dist: tqdm
Requires-Dist: monochrome
Requires-Dist: opencv-contrib-python
Requires-Dist: PySide6
Provides-Extra: test
Requires-Dist: pytest; extra == "test"
Provides-Extra: docs
Requires-Dist: sphinx>=7.4.6; extra == "docs"
Requires-Dist: sphinxcontrib-napoleon; extra == "docs"
Requires-Dist: sphinxcontrib-bibtex; extra == "docs"
Requires-Dist: sphinxcontrib-video; extra == "docs"
Requires-Dist: sphinx-autobuild; extra == "docs"
Requires-Dist: sphinx-copybutton; extra == "docs"
Requires-Dist: sphinx-codeautolink; extra == "docs"
Requires-Dist: furo; extra == "docs"
Requires-Dist: myst_nb>=1.0.0; extra == "docs"
Requires-Dist: jupytext; extra == "docs"
Requires-Dist: jupyter-cache; extra == "docs"
Requires-Dist: sphinx-remove-toctrees; extra == "docs"
Requires-Dist: sphinx-design; extra == "docs"
Requires-Dist: sphinx-togglebutton; extra == "docs"
Dynamic: author
Dynamic: author-email
Dynamic: classifier
Dynamic: description
Dynamic: description-content-type
Dynamic: home-page
Dynamic: license
Dynamic: provides-extra
Dynamic: requires-dist
Dynamic: requires-python
Dynamic: summary
